main.py
data/__init__.py
data/exporter.py
data/handler.py
data/parser.py
data/printer.py
data/saver.py
data/subjects.py
data/utils.py
data/samples/IIIA.xlsx
data/samples/IIIB.xlsx
graphs/__init__.py
graphs/plot_data.py
graphs/plotter.py
graphs/select_graph.py
group/ByPercent.py
group/__init__.py
ui/__init__.py
ui/banners.py
ui/select_data.py
ui/view_data.py
result_analysis-1.0.0.dist-info/METADATA
result_analysis-1.0.0.dist-info/WHEEL
result_analysis-1.0.0.dist-info/entry_points.txt
result_analysis-1.0.0.dist-info/top_level.txt
result_analysis-1.0.0.dist-info/RECORD
