Metadata-Version: 2.4
Name: result-analysis
Version: 1.0.0
Summary: A CLI tool for managing student results from Excel sheets.
Author: Utkarsh Tiwari
Classifier: Programming Language :: Python :: 3
Classifier: License :: OSI Approved :: MIT License
Classifier: Operating System :: OS Independent
Requires-Python: >=3.6
Requires-Dist: pandas>=1.3.0
Requires-Dist: matplotlib>=3.4.0
Requires-Dist: numpy>=1.20.0
Requires-Dist: openpyxl>=3.0.0
Requires-Dist: thefuzz>=0.18.0
Requires-Dist: python-Levenshtein>=0.12.2
Dynamic: author
Dynamic: classifier
Dynamic: description
Dynamic: description-content-type
Dynamic: requires-dist
Dynamic: requires-python
Dynamic: summary
